MANIFEST.in
README.txt
nano.save
setup.cfg
setup.py
v2.theme-configure.zcml
docs/HISTORY.txt
docs/INSTALL.txt
docs/LICENSE.GPL
docs/LICENSE.txt
v2/__init__.py
v2.theme.egg-info/PKG-INFO
v2.theme.egg-info/SOURCES.txt
v2.theme.egg-info/dependency_links.txt
v2.theme.egg-info/entry_points.txt
v2.theme.egg-info/namespace_packages.txt
v2.theme.egg-info/not-zip-safe
v2.theme.egg-info/paster_plugins.txt
v2.theme.egg-info/requires.txt
v2.theme.egg-info/top_level.txt
v2/theme/__init__.py
v2/theme/configure.zcml
v2/theme/migrator.py
v2/theme/profiles.zcml
v2/theme/setuphandlers.py
v2/theme/skins.zcml
v2/theme/tests.py
v2/theme/version.txt
v2/theme/Extensions/Install.py
v2/theme/Extensions/migration.py
v2/theme/browser/__init__.py
v2/theme/browser/configure.zcml
v2/theme/browser/configure.zcml.save
v2/theme/browser/configure.zcml.save.1
v2/theme/browser/configure.zcml.save.2
v2/theme/browser/configureBAK.zcml
v2/theme/browser/form_view.pt
v2/theme/browser/interfaces.py
v2/theme/browser/leadimage-body.pt
v2/theme/browser/one_column_view.pt
v2/theme/browser/one_column_view.py
v2/theme/browser/people_view.pt
v2/theme/browser/people_view.py
v2/theme/browser/person_view.pt
v2/theme/browser/searchview.py
v2/theme/browser/v2_album_view.pt
v2/theme/browser/v2_album_view.py
v2/theme/browser/v2_file.pt
v2/theme/browser/v2_folder_view.pt
v2/theme/browser/v2_folder_view.pt.save
v2/theme/browser/v2_folder_view.py
v2/theme/browser/v2_folder_view2.pt
v2/theme/browser/v2_folder_viewBAK.pt
v2/theme/browser/v2_image_view.pt
v2/theme/browser/v2_image_view.py
v2/theme/browser/v2_people_view.pt
v2/theme/browser/v2_people_view.py
v2/theme/browser/v2_person_view.pt
v2/theme/browser/v2_view.py
v2/theme/browser/view_expanded.pt
v2/theme/browser/view_expanded.py
v2/theme/browser/viewlet.pt
v2/theme/browser/viewlets.py
v2/theme/browser/images/README.txt
v2/theme/browser/javascripts/bg_images.js
v2/theme/browser/javascripts/gallery.js
v2/theme/browser/javascripts/jsFixes.js
v2/theme/browser/javascripts/v2_video.js
v2/theme/browser/stylesheets/README.txt
v2/theme/browser/stylesheets/main.css
v2/theme/browser/templates/global_sections.pt
v2/theme/browser/templates/global_sectionsBAK.pt
v2/theme/browser/templates/v2_folder_view.pt
v2/theme/browser/templates/v2_folder_view.pt.metadata
