Metadata-Version: 1.0
Name: v2.theme
Version: 5.3
Summary: An installable theme for Plone 4
Home-page: https://svn.v2.nl/plone/v2.theme/
Author: David Jonas
Author-email: david@v2.nl
License: GPL
Keywords: web zope plone theme
Platform: UNKNOWN
Classifier: Framework :: Plone
Classifier: Programming Language :: Python
Classifier: Topic :: Software Development :: Libraries :: Python Modules
